langstring/__init__.py
langstring/controller.py
langstring/converter.py
langstring/flags.py
langstring/langstring.py
langstring/multilangstring.py
langstring/py.typed
langstring/setlangstring.py
langstring/utils/__init__.py
langstring/utils/non_instantiable.py
langstring/utils/validators.py
langstring-3.0.2.dist-info/LICENSE
langstring-3.0.2.dist-info/METADATA
langstring-3.0.2.dist-info/WHEEL
langstring-3.0.2.dist-info/RECORD
