Metadata-Version: 2.1
Name: langstring
Version: 3.0.2
Summary: LangString Python Library
Home-page: https://github.com/pedropaulofb/langstring
License: Apache-2.0
Keywords: string,langstring,multilangstring,language-string,multilanguage-string,language-representation,multilanguage
Author: Pedro Paulo F. Barcelos
Author-email: p.p.favatobarcelos@utwente.nl
Requires-Python: >=3.11,<4.0
Classifier: License :: OSI Approved :: Apache Software License
Classifier: Programming Language :: Python :: 3
Classifier: Programming Language :: Python :: 3.11
Classifier: Programming Language :: Python :: 3.12
Provides-Extra: langcodes
Requires-Dist: langcodes (>=3.3.0,<4.0.0) ; extra == "langcodes"
Project-URL: Documentation, https://pedropaulofb.github.io/langstring
Project-URL: PyPi Project, https://pypi.org/project/langstring/
Project-URL: Repository, https://github.com/pedropaulofb/langstring
